mbnk/__init__.py
mbnk/client/__init__.py
mbnk/client/client.py
mbnk/client/context.py
mbnk/client/session/__init__.py
mbnk/client/session/base.py
mbnk/client/session/middlewares/__init__.py
mbnk/client/session/middlewares/base.py
mbnk/client/session/middlewares/manager.py
mbnk/client/session/session.py
mbnk/enums/__init__.py
mbnk/enums/account_type.py
mbnk/enums/amount_type.py
mbnk/enums/cancellation_status.py
mbnk/enums/cashback_type.py
mbnk/enums/currency_code.py
mbnk/enums/payment_method.py
mbnk/enums/payment_scheme.py
mbnk/enums/payment_type.py
mbnk/enums/registration_status.py
mbnk/enums/tokenized_card_status.py
mbnk/enums/transaction_status.py
mbnk/exceptions.py
mbnk/methods/__init__.py
mbnk/methods/base.py
mbnk/methods/cancel_invoice.py
mbnk/methods/create_invoice.py
mbnk/methods/delete_card.py
mbnk/methods/direct_payment.py
mbnk/methods/finalize_invoice.py
mbnk/methods/fiscal_checks.py
mbnk/methods/invoice_status.py
mbnk/methods/merchant_details.py
mbnk/methods/merchant_statement.py
mbnk/methods/payment_info.py
mbnk/methods/qr_details.py
mbnk/methods/qr_list.py
mbnk/methods/qr_reset_amount.py
mbnk/methods/remove_invoice.py
mbnk/methods/submerchant_list.py
mbnk/methods/wallet_cards.py
mbnk/methods/wallet_payment.py
mbnk/mono.py
mbnk/types/__init__.py
mbnk/types/account.py
mbnk/types/base.py
mbnk/types/canceled_item.py
mbnk/types/currency.py
mbnk/types/empty_response.py
mbnk/types/invoice_canceled.py
mbnk/types/invoice_created.py
mbnk/types/invoice_status.py
mbnk/types/jar.py
mbnk/types/merchant_details.py
mbnk/types/merchant_paym_info.py
mbnk/types/merchant_pubkey.py
mbnk/types/merchant_statement.py
mbnk/types/merchant_statement_item.py
mbnk/types/product.py
mbnk/types/save_card_data.py
mbnk/types/transaction.py
mbnk/types/wallet_data.py
mbnk/types/wallet_item.py
mbnk/types/wallet_list.py
mbnk/types1.py
mbnk/utils/__init__.py
mbnk/utils/secrets.py
mbnk/utils/webhook.py
mbnk-0.4.2.dist-info/METADATA
mbnk-0.4.2.dist-info/WHEEL
mbnk-0.4.2.dist-info/RECORD
