Metadata-Version: 2.1
Name: mbnk
Version: 0.4.2
Summary: Sync/Async version Monobank api
License: MIT
Author: yeghorkikhai
Author-email: yeghorkikhai@gmail.com
Requires-Python: >=3.11,<4.0
Classifier: License :: OSI Approved :: MIT License
Classifier: Programming Language :: Python :: 3
Classifier: Programming Language :: Python :: 3.11
Requires-Dist: aiohttp (>=3.8.4,<4.0.0)
Requires-Dist: ecdsa (>=0.18.0,<0.19.0)
Requires-Dist: pydantic (>=2.0.2,<3.0.0)
Requires-Dist: pytest (>=7.4.0,<8.0.0)
Requires-Dist: requests (>=2.31.0,<3.0.0)
